interana/_version.py
interana/__init__.py
interana/ia.py
interana/utils/config.py
interana/utils/samples.py
interana/utils/shared_parsers.py
interana/utils/completers.py
interana/utils/__init__.py
interana/utils/command_utils.py
interana/commands/config.py
interana/commands/purge.py
interana/commands/tier.py
interana/commands/data.py
interana/commands/lookup.py
interana/commands/column.py
interana/commands/job.py
interana/commands/__init__.py
interana/commands/node.py
interana/commands/base.py
interana/commands/user.py
interana/commands/pipeline.py
interana/commands/email_domain.py
interana/commands/table.py
interana/commands/settings.py
interana_cli-2.25.0.dist-info/entry_points.txt
interana_cli-2.25.0.dist-info/WHEEL
interana_cli-2.25.0.dist-info/METADATA
interana_cli-2.25.0.dist-info/top_level.txt
interana_cli-2.25.0.dist-info/metadata.json
interana_cli-2.25.0.dist-info/RECORD
interana_cli-2.25.0.dist-info/DESCRIPTION.rst
