Metadata-Version: 2.0
Name: interana-cli
Version: 2.25.0
Summary: Administration for a customer's Interana deployment
Home-page: http://github.com/Interana/backend
Author: Interana
Author-email: support@interana.com
License: MIT
Platform: UNKNOWN
Requires-Dist: requests (>=2.9.1)
Requires-Dist: tabulate (>=0.7.5)
Requires-Dist: argcomplete (>=1.1.1)
Requires-Dist: pyOpenSSL (>=17.2.0)
Requires-Dist: ndg-httpsclient (>=0.4.2)
Requires-Dist: pyasn1 (>=0.3.2)
